setup.py
lazycontract/__init__.py
lazycontract/contract.py
lazycontract/extra.py
lazycontract/properties.py
lazycontract/test_contract.py
lazycontract/test_extra.py
lazycontract/test_properties.py
lazycontract.egg-info/PKG-INFO
lazycontract.egg-info/SOURCES.txt
lazycontract.egg-info/dependency_links.txt
lazycontract.egg-info/requires.txt
lazycontract.egg-info/top_level.txt