Metadata-Version: 1.1
Name: lazycontract
Version: 0.9.4
Summary: Python library to define declarative contracts for serialization and deserialization
Home-page: https://github.com/neilisaac/lazycontract
Author: Neil Isaac
Author-email: isaac.neil@gmail.com
License: MIT
Platform: Any
Classifier: Intended Audience :: Developers
Classifier: License :: OSI Approved :: MIT License
Classifier: Programming Language :: Python :: 2.7
Classifier: Programming Language :: Python :: 3.2
Classifier: Programming Language :: Python :: 3.3
Classifier: Programming Language :: Python :: 3.4
Classifier: Topic :: Software Development :: Libraries
